mopidy_mixcloud/__init__.py
mopidy_mixcloud/cache.py
mopidy_mixcloud/ext.conf
mopidy_mixcloud/mixcloud_data.py
mopidy_mixcloud/mopidy_mixcloud.py
mopidy_mixcloud/uris.py
mopidy_mixcloud/util.py
Mopidy_Mixcloud-3.1415.9265.dist-info/LICENSE
Mopidy_Mixcloud-3.1415.9265.dist-info/METADATA
Mopidy_Mixcloud-3.1415.9265.dist-info/WHEEL
Mopidy_Mixcloud-3.1415.9265.dist-info/entry_points.txt
Mopidy_Mixcloud-3.1415.9265.dist-info/top_level.txt
Mopidy_Mixcloud-3.1415.9265.dist-info/RECORD
