Metadata-Version: 2.1
Name: Mopidy-Mixcloud
Version: 3.1415.9265
Summary: Mopidy Mixcloud extension
Home-page: https://github.com/unusualcomputers/unusualcomputers/tree/master/code/mopidy/mopidymixcloud
Author: Unusual Computers
Author-email: unusual.computers@gmail.com
License: Apache License, Version 2.0
Platform: UNKNOWN
Classifier: Environment :: No Input/Output (Daemon)
Classifier: Intended Audience :: End Users/Desktop
Classifier: License :: OSI Approved :: Apache Software License
Classifier: Operating System :: OS Independent
Classifier: Programming Language :: Python :: 2
Classifier: Topic :: Multimedia :: Sound/Audio :: Players
Requires-Dist: Mopidy (>=1.0)
Requires-Dist: Pykka (>=1.1)
Requires-Dist: setuptools
Requires-Dist: youtube-dl (>=2020.6.16.1)
